NepseData/__init__.py
NepseData-1.2.dist-info/METADATA
NepseData-1.2.dist-info/WHEEL
NepseData-1.2.dist-info/top_level.txt
NepseData-1.2.dist-info/RECORD
