Metadata-Version: 2.1
Name: NepseData
Version: 1.2
Summary: Every information and data in Nepal Share Market are available
Home-page: UNKNOWN
Author: Anup Timsina
Author-email: UNKNOWN
License: UNKNOWN
Platform: UNKNOWN
Requires-Dist: requests
Requires-Dist: bs4
Requires-Dist: lxml
